{
  "entities": {
    "User": {
      "title": "User Profile",
      "description": "User profile information and settings",
      "type": "object",
      "properties": {
        "uid": { "type": "string" },
        "displayName": { "type": "string" },
        "email": { "type": "string" },
        "phoneNumber": { "type": "string" },
        "emergencyContacts": {
          "type": "array",
          "items": {
            "type": "object",
            "properties": {
              "name": { "type": "string" },
              "phone": { "type": "string" },
              "relation": { "type": "string" }
            }
          }
        },
        "createdAt": { "type": "string", "format": "date-time" }
      },
      "required": ["uid", "email"]
    },
    "SOSAlert": {
      "title": "SOS Alert",
      "description": "Active distress signals from users",
      "type": "object",
      "properties": {
        "userId": { "type": "string" },
        "userName": { "type": "string" },
        "location": {
          "type": "object",
          "properties": {
            "latitude": { "type": "number" },
            "longitude": { "type": "number" }
          }
        },
        "status": { "type": "string", "enum": ["active", "resolved"] },
        "timestamp": { "type": "string", "format": "date-time" }
      },
      "required": ["userId", "location", "status", "timestamp"]
    },
    "Incident": {
      "title": "Safety Incident",
      "description": "Community reported safety incidents or unsafe areas",
      "type": "object",
      "properties": {
        "reporterId": { "type": "string" },
        "type": { "type": "string", "enum": ["harassment", "unsafe-area", "theft", "other"] },
        "description": { "type": "string" },
        "location": {
          "type": "object",
          "properties": {
            "latitude": { "type": "number" },
            "longitude": { "type": "number" },
            "address": { "type": "string" }
          }
        },
        "timestamp": { "type": "string", "format": "date-time" }
      },
      "required": ["reporterId", "type", "location", "timestamp"]
    }
  },
  "firestore": {
    "/users/{userId}": {
      "schema": "User",
      "description": "User profile documents"
    },
    "/alerts/{alertId}": {
      "schema": "SOSAlert",
      "description": "Active SOS alerts"
    },
    "/incidents/{incidentId}": {
      "schema": "Incident",
      "description": "Community incident reports"
    }
  }
}
